chatlocal-0.1.3.dist-info/METADATA
chatlocal-0.1.3.dist-info/WHEEL
chatlocal/__init__.py
chatlocal/dataloader.py
chatlocal/settings.py
chatlocal/vectorstore.py
chatlocal-0.1.3.dist-info/RECORD
