Metadata-Version: 2.1
Name: chatlocal
Version: 0.1.3
Summary: chat with your local files
Author-Email: Raoul Grouls <Raoul.Grouls@han.nl>
License: MIT
Project-URL: Github, https://github.com/raoulg/chatlocal
Requires-Python: <3.11,>=3.9
Requires-Dist: langchain>=0.0.295
Requires-Dist: openai>=0.28.0
Requires-Dist: faiss-cpu>=1.7.4
Requires-Dist: streamlit>=1.12.0
Requires-Dist: loguru>=0.7.2
Requires-Dist: pdftotext>=2.2.2
Requires-Dist: streamlit-chat>=0.1.1
Requires-Dist: tiktoken>=0.5.1
Requires-Dist: python-docx>=0.8.11
Requires-Dist: toml>=0.10.2
